perceptual_advex/__init__.py
perceptual_advex/attacks.py
perceptual_advex/datasets.py
perceptual_advex/distances.py
perceptual_advex/evaluation.py
perceptual_advex/models.py
perceptual_advex/perceptual_attacks.py
perceptual_advex/py.typed
perceptual_advex/trades_wrn.py
perceptual_advex/utilities.py
perceptual_advex-0.2.6.dist-info/LICENSE.txt
perceptual_advex-0.2.6.dist-info/METADATA
perceptual_advex-0.2.6.dist-info/WHEEL
perceptual_advex-0.2.6.dist-info/top_level.txt
perceptual_advex-0.2.6.dist-info/RECORD
