Metadata-Version: 2.1
Name: perceptual-advex
Version: 0.2.6
Summary: Code for the ICLR 2021 paper "Perceptual Adversarial Robustness: Defense Against Unseen Threat Models"
Home-page: https://github.com/cassidylaidlaw/perceptual-advex
Author: Cassidy Laidlaw
Author-email: claidlaw@umd.edu
License: MIT
Download-URL: https://github.com/cassidylaidlaw/perceptual-advex/archive/TODO.tar.gz
Keywords: adversarial examples,machine learning
Platform: UNKNOWN
Classifier: Development Status :: 3 - Alpha
Classifier: Intended Audience :: Science/Research
Classifier: Topic :: Scientific/Engineering :: Artificial Intelligence
Classifier: Topic :: Scientific/Engineering :: Image Recognition
Classifier: License :: OSI Approved :: MIT License
Classifier: Programming Language :: Python :: 3
Classifier: Programming Language :: Python :: 3.6
Classifier: Programming Language :: Python :: 3.7
Classifier: Programming Language :: Python :: 3.8
Classifier: Programming Language :: Python :: 3.9
Requires-Dist: torch (>=1.4.0)
Requires-Dist: robustness (>=1.1.post2)
Requires-Dist: numpy (>=1.18.2)
Requires-Dist: torchvision (>=0.5.0)
Requires-Dist: PyWavelets (>=1.0.0)
Requires-Dist: advex-uar (>=0.0.5.dev0)
Requires-Dist: statsmodels (==0.11.1)
Requires-Dist: recoloradv (==0.0.1)
